<?xml version="1.0" encoding="UTF-8"?><record_update table="sys_db_object">
    <sys_db_object action="DELETE">
        <access/>
        <actions_access>true</actions_access>
        <alter_access>true</alter_access>
        <caller_access/>
        <client_scripts_access>true</client_scripts_access>
        <configuration_access>false</configuration_access>
        <create_access>true</create_access>
        <create_access_controls>false</create_access_controls>
        <delete_access>false</delete_access>
        <extension_model/>
        <is_extendable>false</is_extendable>
        <label>Spaces</label>
        <live_feed_enabled>false</live_feed_enabled>
        <name>x_snc_flight_pla_0_spaces</name>
        <number_ref/>
        <provider_class/>
        <read_access>true</read_access>
        <scriptable_table>false</scriptable_table>
        <super_class display_value="Task" name="task">5e856ca7551201107f44d7f62dcafeb1</super_class>
        <sys_class_code/>
        <sys_class_name>sys_db_object</sys_class_name>
        <sys_class_path/>
        <sys_created_by>admin</sys_created_by>
        <sys_created_on>2022-10-19 17:55:50</sys_created_on>
        <sys_id>88e0e60f41a611107f44064b62c9ce4b</sys_id>
        <sys_mod_count>0</sys_mod_count>
        <sys_name>Flight Pla 0 Spaces</sys_name>
        <sys_package display_value="Flight Plan App" source="x_snc_flight_pla_0">aab9920741a611107f44064b62c9ce79</sys_package>
        <sys_policy/>
        <sys_scope display_value="Flight Plan App">aab9920741a611107f44064b62c9ce79</sys_scope>
        <sys_update_name>sys_db_object_88e0e60f41a611107f44064b62c9ce4b</sys_update_name>
        <sys_updated_by>admin</sys_updated_by>
        <sys_updated_on>2022-10-19 17:55:50</sys_updated_on>
        <update_access>true</update_access>
        <user_role/>
        <ws_access>true</ws_access>
    </sys_db_object>
    <sys_update_version action="INSERT_OR_UPDATE">
        <action>DELETE</action>
        <application display_value="Flight Plan App">aab9920741a611107f44064b62c9ce79</application>
        <file_path/>
        <instance_id>0a71f7a6c36a959065d9d0f4e401315a</instance_id>
        <instance_name>sad-oct-475-007</instance_name>
        <name>sys_db_object_88e0e60f41a611107f44064b62c9ce4b</name>
        <payload><![CDATA[<?xml version="1.0" encoding="UTF-8"?><record_update table="sys_db_object"><sys_db_object action="INSERT_OR_UPDATE"><access/><actions_access>true</actions_access><alter_access>true</alter_access><caller_access/><client_scripts_access>true</client_scripts_access><configuration_access>false</configuration_access><create_access>true</create_access><create_access_controls>false</create_access_controls><delete_access>false</delete_access><extension_model/><is_extendable>false</is_extendable><label>Spaces</label><live_feed_enabled>false</live_feed_enabled><name>x_snc_flight_pla_0_spaces</name><number_ref/><provider_class/><read_access>true</read_access><scriptable_table>false</scriptable_table><super_class display_value="Task" name="task">5e856ca7551201107f44d7f62dcafeb1</super_class><sys_class_code/><sys_class_name>sys_db_object</sys_class_name><sys_class_path/><sys_created_by>admin</sys_created_by><sys_created_on>2022-10-19 17:55:50</sys_created_on><sys_id>88e0e60f41a611107f44064b62c9ce4b</sys_id><sys_mod_count>0</sys_mod_count><sys_name>Flight Pla 0 Spaces</sys_name><sys_package display_value="Flight Plan App" source="x_snc_flight_pla_0">aab9920741a611107f44064b62c9ce79</sys_package><sys_policy/><sys_scope display_value="Flight Plan App">aab9920741a611107f44064b62c9ce79</sys_scope><sys_update_name>sys_db_object_88e0e60f41a611107f44064b62c9ce4b</sys_update_name><sys_updated_by>admin</sys_updated_by><sys_updated_on>2022-10-19 17:55:50</sys_updated_on><update_access>true</update_access><user_role/><ws_access>true</ws_access></sys_db_object></record_update>]]></payload>
        <payload_hash>1772849072</payload_hash>
        <record_name>Spaces</record_name>
        <reverted_from/>
        <source>62b9920741a611107f44064b62c9ce7c</source>
        <source_table>sys_update_set</source_table>
        <state>previous</state>
        <sys_created_by>admin</sys_created_by>
        <sys_created_on>2022-10-19 17:55:50</sys_created_on>
        <sys_id>0ce0e60f41a611107f44064b62c9ce6a</sys_id>
        <sys_mod_count>0</sys_mod_count>
        <sys_recorded_at>183f16328530000001</sys_recorded_at>
        <sys_updated_by>admin</sys_updated_by>
        <sys_updated_on>2022-10-19 17:55:50</sys_updated_on>
        <type>Table</type>
        <update_guid>84e0e60ff6a6111038ae81313e5ef26a</update_guid>
        <update_guid_history>84e0e60ff6a6111038ae81313e5ef26a:1772849072</update_guid_history>
    </sys_update_version>
    <sys_metadata_delete action="INSERT_OR_UPDATE">
        <sys_audit_delete/>
        <sys_class_name>sys_metadata_delete</sys_class_name>
        <sys_created_by>admin</sys_created_by>
        <sys_created_on>2022-10-19 17:56:22</sys_created_on>
        <sys_db_object display_value="" name="sys_db_object">sys_db_object</sys_db_object>
        <sys_id>1b3d2ae9830745b0a3f87e22bc310c04</sys_id>
        <sys_metadata>88e0e60f41a611107f44064b62c9ce4b</sys_metadata>
        <sys_mod_count>0</sys_mod_count>
        <sys_name>Spaces</sys_name>
        <sys_package display_value="Flight Plan App" source="x_snc_flight_pla_0">aab9920741a611107f44064b62c9ce79</sys_package>
        <sys_parent/>
        <sys_policy/>
        <sys_scope display_value="Flight Plan App">aab9920741a611107f44064b62c9ce79</sys_scope>
        <sys_scope_delete display_value="">01cd9d9b19fd424380178a96b38d9609</sys_scope_delete>
        <sys_update_name>sys_db_object_88e0e60f41a611107f44064b62c9ce4b</sys_update_name>
        <sys_update_version display_value="sys_db_object_88e0e60f41a611107f44064b62c9ce4b">0ce0e60f41a611107f44064b62c9ce6a</sys_update_version>
        <sys_updated_by>admin</sys_updated_by>
        <sys_updated_on>2022-10-19 17:56:22</sys_updated_on>
    </sys_metadata_delete>
</record_update>
